example_scripts/apply_ahf.py
example_scripts/gadget3_hdf5.py
cosmic_profiles/__init__.pxd
cosmic_profiles/__init__.py
cosmic_profiles/for_docs/setup_compile.py
cosmic_profiles/for_docs/dens_profs/__init__.pxd
cosmic_profiles/for_docs/dens_profs/dens_profs_algos.pyx
cosmic_profiles/for_docs/dens_profs/dens_profs_classes.pyx
cosmic_profiles/for_docs/dens_profs/dens_profs_classes.pxd
cosmic_profiles/for_docs/dens_profs/dens_profs_tools.py
cosmic_profiles/for_docs/shape_profs/shape_profs_algos.pyx
cosmic_profiles/for_docs/shape_profs/shape_profs_tools.py
cosmic_profiles/for_docs/shape_profs/shape_profs_classes.pyx
cosmic_profiles/for_docs/gadget/readgadget.py
cosmic_profiles/for_docs/gadget/readsnap.py
cosmic_profiles/for_docs/gadget/read_fof.py
cosmic_profiles/for_docs/gadget/gen_catalogues.pyx
cosmic_profiles/for_docs/cython_helpers/helper_class.pyx
cosmic_profiles/for_docs/mock_tools/mock_uni.py
cosmic_profiles/for_docs/mock_tools/mock_halo_gen.py
cosmic_profiles/for_docs/common/__init__.pxd
cosmic_profiles/for_docs/common/cosmic_base_class.pxd
cosmic_profiles/for_docs/common/caching.py
cosmic_profiles/for_docs/common/__init__.py
cosmic_profiles/for_docs/common/config.py
cosmic_profiles/for_docs/common/python_routines.py
cosmic_profiles/for_docs/common/cosmic_base_class.pyx
cosmic_profiles/for_docs/common/cosmo_tools.py
cosmic_profiles/dens_profs/__init__.pxd
cosmic_profiles/dens_profs/dens_profs_classes.c
cosmic_profiles/dens_profs/dens_profs_algos.pyx
cosmic_profiles/dens_profs/dens_profs_classes.pyx
cosmic_profiles/dens_profs/dens_profs_classes.pxd
cosmic_profiles/dens_profs/dens_profs_tools.py
cosmic_profiles/dens_profs/dens_profs_algos.so
cosmic_profiles/dens_profs/dens_profs_classes.so
cosmic_profiles/dens_profs/dens_profs_algos.c
cosmic_profiles/shape_profs/__init__.pxd
cosmic_profiles/shape_profs/shape_profs_algos.pyx
cosmic_profiles/shape_profs/shape_profs_algos.so
cosmic_profiles/shape_profs/shape_profs_classes.c
cosmic_profiles-1.4.0.dist-info/LICENSE.md
cosmic_profiles-1.4.0.dist-info/top_level.txt
cosmic_profiles-1.4.0.dist-info/RECORD
cosmic_profiles-1.4.0.dist-info/WHEEL
cosmic_profiles-1.4.0.dist-info/METADATA
