Metadata-Version: 2.1
Name: cosmic-profiles
Version: 1.4.0
Summary: Implements 3D point cloud algorithms for estimation and fitting of shape and density profiles
Author: Tibor Dome
Author-email: tibor.doeme@gmail.com
License: MIT
Project-URL: Documentation, https://cosmic-profiles.readthedocs.io/en/latest/
Project-URL: Source, https://github.com/tibordome/cosmic_profiles
Classifier: License :: OSI Approved :: MIT License
Classifier: Programming Language :: Python :: 3
Classifier: Programming Language :: Python :: 3.7
Classifier: Intended Audience :: Science/Research
Classifier: Operating System :: POSIX
Classifier: Topic :: Scientific/Engineering :: Astronomy
Classifier: Topic :: Scientific/Engineering :: Visualization
License-File: LICENSE.md
Requires-Dist: cython
Requires-Dist: cythongsl
Requires-Dist: numpy (>=1.19.2)
Requires-Dist: scipy
Requires-Dist: pathos
Requires-Dist: scikit-learn
Requires-Dist: mpi4py
Requires-Dist: h5py
Requires-Dist: matplotlib
Requires-Dist: psutil
